notify_bridge-0.8.0.dist-info/METADATA
notify_bridge-0.8.0.dist-info/WHEEL
notify_bridge-0.8.0.dist-info/entry_points.txt
notify_bridge-0.8.0.dist-info/licenses/LICENSE
notify_bridge/__init__.py
notify_bridge/components.py
notify_bridge/core.py
notify_bridge/exceptions.py
notify_bridge/factory.py
notify_bridge/notifiers/__init__.py
notify_bridge/notifiers/feishu.py
notify_bridge/notifiers/github.py
notify_bridge/notifiers/notify.py
notify_bridge/notifiers/wecom.py
notify_bridge/plugin.py
notify_bridge/schema.py
notify_bridge/utils.py
notify_bridge-0.8.0.dist-info/RECORD
