Metadata-Version: 2.1
Name: notify-bridge
Version: 0.8.0
Summary: A bridge for sending notifications to various platforms
Keywords: notification,bridge,feishu,dingtalk,wechat
Author-Email: Long Hao <hal.long@outlook.com>
License: MIT License
Classifier: Development Status :: 3 - Alpha
Classifier: Intended Audience :: Developers
Classifier: License :: OSI Approved :: MIT License
Classifier: Programming Language :: Python :: 3
Classifier: Programming Language :: Python :: 3.8
Classifier: Programming Language :: Python :: 3.9
Classifier: Programming Language :: Python :: 3.10
Classifier: Programming Language :: Python :: 3.11
Classifier: Programming Language :: Python :: 3.12
Project-URL: Homepage, https://github.com/loonghao/notify-bridge
Project-URL: Documentation, https://github.com/loonghao/notify-bridge#readme
Project-URL: Repository, https://github.com/loonghao/notify-bridge.git
Project-URL: Issues, https://github.com/loonghao/notify-bridge/issues
Requires-Python: >=3.8
Requires-Dist: anyio>=4.0.0
Requires-Dist: httpx>=0.26.0
Requires-Dist: pydantic[email]>=2.5.3
Requires-Dist: pillow>=10.0.0
Requires-Dist: aiofiles>=23.2.1
Provides-Extra: dev
Requires-Dist: pytest>=7.4.4; extra == "dev"
Requires-Dist: pytest-cov>=4.0.0; extra == "dev"
Requires-Dist: black>=23.0.0; extra == "dev"
Requires-Dist: isort>=5.0.0; extra == "dev"
Requires-Dist: mypy>=1.0.0; extra == "dev"
Requires-Dist: ruff>=0.1.0; extra == "dev"
Requires-Dist: python-dotenv>=1.0.0; extra == "dev"
Requires-Dist: pre-commit>=3.0.0; extra == "dev"
